{
  "kind": "singleType",
  "collectionName": "works",
  "info": {
    "singularName": "work",
    "pluralName": "works",
    "displayName": "Work"
  },
  "options": {
    "draftAndPublish": true
  },
  "pluginOptions": {},
  "attributes": {
    "BannerHeading": {
      "type": "customField",
      "customField": "plugin::ckeditor5.CKEditor",
      "options": {
        "preset": "defaultHtml"
      }
    },
    "Work_History": {
      "type": "component",
      "component": "work.work-history",
      "repeatable": true
    },
    "Testimonials": {
      "type": "component",
      "component": "talent-executive.section6",
      "repeatable": false
    },
    "Slider": {
      "type": "component",
      "component": "service.slider",
      "repeatable": true
    },
    "Results": {
      "type": "component",
      "component": "home.results",
      "repeatable": false
    },
    "PageTitle": {
      "type": "string"
    },
    "seo": {
      "type": "component",
      "component": "shared.seo",
      "repeatable": false
    }
  }
}
